lcdp_api/__init__.py
lcdp_api/event/__init__.py
lcdp_api/event/configuration/Variable/Key.avsc
lcdp_api/event/configuration/Variable/Value.avsc
lcdp_api/event/favorite/FavoriteProduct/Key.avsc
lcdp_api/event/favorite/FavoriteProduct/Value.avsc
lcdp_api/event/laboratory/Laboratory/Key.avsc
lcdp_api/event/laboratory/Laboratory/Value.avsc
lcdp_api/event/product/Product/Key.avsc
lcdp_api/event/product/Product/Value.avsc
lcdp_api/event/product/SecondaryType/Key.avsc
lcdp_api/event/product/SecondaryType/Value.avsc
lcdp_api/event/product/Type/Key.avsc
lcdp_api/event/product/Type/Value.avsc
lcdp_api/event/product/Vat/Key.avsc
lcdp_api/event/product/Vat/Value.avsc
lcdp_api/event/sale-offer/AnyIdentifiedDistributionMode/Value.avsc
lcdp_api/event/sale-offer/IdentifiedDistributionRange/Value.avsc
lcdp_api/event/sale-offer/SaleOffer/Key.avsc
lcdp_api/event/sale-offer/SaleOffer/Value.avsc
lcdp_api/event/statistic/SaleOfferStatistic/Key.avsc
lcdp_api/event/statistic/SaleOfferStatistic/Value.avsc
lcdp_api/event/statistic/UserStatistic/Key.avsc
lcdp_api/event/statistic/UserStatistic/Value.avsc
lcdp_api/event/storage/Stock/Key.avsc
lcdp_api/event/storage/Stock/Value.avsc
lcdp_api/event/user/Transport/Value.avsc
lcdp_api/event/user/User/Key.avsc
lcdp_api/event/user/User/Value.avsc
lcdp_api/rest/__init__.py
lcdp_api/rest/auth.yaml
lcdp_api/rest/banking-operation.yaml
lcdp_api/rest/catalog.yaml
lcdp_api/rest/challenge.yaml
lcdp_api/rest/chargebee-hook.yaml
lcdp_api/rest/common.yaml
lcdp_api/rest/configuration.yaml
lcdp_api/rest/content.yaml
lcdp_api/rest/factory.yaml
lcdp_api/rest/favorite.yaml
lcdp_api/rest/geo.yaml
lcdp_api/rest/inventory.yaml
lcdp_api/rest/invoice.yaml
lcdp_api/rest/laboratory-store-log.yaml
lcdp_api/rest/laboratory-store.yaml
lcdp_api/rest/laboratory.yaml
lcdp_api/rest/lexicon.yaml
lcdp_api/rest/litigation.yaml
lcdp_api/rest/magic-cart.yaml
lcdp_api/rest/mandate.yaml
lcdp_api/rest/mangopay-hook.yaml
lcdp_api/rest/message.yaml
lcdp_api/rest/notification.yaml
lcdp_api-1.12.29.dist-info/LICENSE.md
lcdp_api-1.12.29.dist-info/METADATA
lcdp_api-1.12.29.dist-info/WHEEL
lcdp_api-1.12.29.dist-info/top_level.txt
lcdp_api-1.12.29.dist-info/RECORD
