Metadata-Version: 2.1
Name: lcdp-api
Version: 1.12.29
Summary: Rest api specification for Le Comptoir Des Pharmacies
Home-page: https://bitbucket.org/lecomptoirdespharmacies/lcdp-api
Author: Le Comptoir Des Pharmacies
Author-email: g.thrasibule@lecomptoirdespharmacies.fr
License: Apache-2.0
Keywords: openapi,rest-api,rest,openapi3
Platform: UNKNOWN
License-File: LICENSE.md
